jupyterlab_multicontents_templates/__init__.py
jupyterlab_multicontents_templates/_version.py
jupyterlab_multicontents_templates/handlers.py
jupyterlab_multicontents_templates/labextension/package.json
jupyterlab_multicontents_templates/labextension/static/147.d3bf9571cff08453d675.js
jupyterlab_multicontents_templates/labextension/static/728.de7fbf6989663a3a532e.js
jupyterlab_multicontents_templates/labextension/static/remoteEntry.a510c1fff63cd2d07628.js
jupyterlab_multicontents_templates/labextension/static/style.js
jupyterlab_multicontents_templates/labextension/static/third-party-licenses.json
jupyterlab_multicontents_templates-0.4.9.data/data/etc/jupyter/jupyter_server_config.d/jupyterlab_multicontents_templates.json
jupyterlab_multicontents_templates-0.4.9.data/data/share/jupyter/labextensions/jupyterlab_multicontents_templates/install.json
jupyterlab_multicontents_templates-0.4.9.data/data/share/jupyter/labextensions/jupyterlab_multicontents_templates/package.json
jupyterlab_multicontents_templates-0.4.9.data/data/share/jupyter/labextensions/jupyterlab_multicontents_templates/static/147.d3bf9571cff08453d675.js
jupyterlab_multicontents_templates-0.4.9.data/data/share/jupyter/labextensions/jupyterlab_multicontents_templates/static/728.de7fbf6989663a3a532e.js
jupyterlab_multicontents_templates-0.4.9.data/data/share/jupyter/labextensions/jupyterlab_multicontents_templates/static/remoteEntry.a510c1fff63cd2d07628.js
jupyterlab_multicontents_templates-0.4.9.data/data/share/jupyter/labextensions/jupyterlab_multicontents_templates/static/style.js
jupyterlab_multicontents_templates-0.4.9.data/data/share/jupyter/labextensions/jupyterlab_multicontents_templates/static/third-party-licenses.json
jupyterlab_multicontents_templates-0.4.9.dist-info/LICENSE
jupyterlab_multicontents_templates-0.4.9.dist-info/METADATA
jupyterlab_multicontents_templates-0.4.9.dist-info/WHEEL
jupyterlab_multicontents_templates-0.4.9.dist-info/top_level.txt
jupyterlab_multicontents_templates-0.4.9.dist-info/RECORD
