Metadata-Version: 2.1
Name: jupyterlab-multicontents-templates
Version: 0.4.9
Summary: Jupyterlab templates from different types of contentsmanager 
Home-page: https://github.com/lydian/jupyterlab_multicontents_templates
Author: Lydian Lee
Author-email: lydianly@gmail.com
License: BSD-3-Clause
Keywords: Jupyter,JupyterLab,JupyterLab3
Platform: Linux
Platform: Mac OS X
Platform: Windows
Classifier: License :: OSI Approved :: BSD License
Classifier: Programming Language :: Python
Classifier: Programming Language :: Python :: 3
Classifier: Programming Language :: Python :: 3.6
Classifier: Programming Language :: Python :: 3.7
Classifier: Programming Language :: Python :: 3.8
Classifier: Programming Language :: Python :: 3.9
Classifier: Framework :: Jupyter
Requires-Python: >=3.9
License-File: LICENSE
Requires-Dist: jupyterlab~=4.2
Requires-Dist: multicontents
Requires-Dist: nbconvert
Requires-Dist: traitlets
Requires-Dist: nbformat
Requires-Dist: tornado
Requires-Dist: jupyter-server
Requires-Dist: IPython
Requires-Dist: jupyter-packaging~=0.7.9
